README.md
cyborgdb_lite/__init__.py
cyborgdb_lite/cyborgdb_lite.cpython-312-aarch64-linux-gnu.so
cyborgdb_lite/cyborgdb_lite.pyi
cyborgdb_lite/integrations/__init__.py
cyborgdb_lite.libs/libarmadillo-16b6d3eb.so.12.6.6
cyborgdb_lite.libs/libarpack-7c977886.so.2.1.0
cyborgdb_lite.libs/libblas-8ed0a6f9.so.3.8.0
cyborgdb_lite.libs/libbrotlicommon-b6e6c8bd.so.1.0.6
cyborgdb_lite.libs/libbrotlidec-5094ef0a.so.1.0.6
cyborgdb_lite.libs/libcom_err-4b53f6ce.so.2.1
cyborgdb_lite.libs/libcrypt-258f54d5.so.1.1.0
cyborgdb_lite.libs/libcrypto-3dc39733.so.1.1.1k
cyborgdb_lite.libs/libcurl-37295c13.so.4.5.0
cyborgdb_lite.libs/libgfortran-8a9a71bc.so.5.0.0
cyborgdb_lite.libs/libgomp-947d5fa1.so.1.0.0
cyborgdb_lite.libs/libgssapi_krb5-fe951f80.so.2.2
cyborgdb_lite.libs/libhiredis-3032ecd8.so.1.3.0
cyborgdb_lite.libs/libhiredis_ssl-786690ac.so.1.3.0
cyborgdb_lite.libs/libidn2-1b2a13b7.so.0.3.6
cyborgdb_lite.libs/libk5crypto-84470bb3.so.3.1
cyborgdb_lite.libs/libkeyutils-fe6e95a9.so.1.6
cyborgdb_lite.libs/libkrb5-26ef5d84.so.3.3
cyborgdb_lite.libs/libkrb5support-875e89dc.so.0.1
cyborgdb_lite.libs/liblapack-8d137073.so.3.8.0
cyborgdb_lite.libs/liblber-2-86b08e65.4.so.2.10.9
cyborgdb_lite.libs/libldap-2-5c1dd279.4.so.2.10.9
cyborgdb_lite.libs/libldap_r-2-582a282c.4.so.2.10.9
cyborgdb_lite.libs/libnghttp2-3a94c239.so.14.17.0
cyborgdb_lite.libs/libopenblas-r0-e9c9f581.3.15.so
cyborgdb_lite.libs/libopenblaso-r0-e4adfc97.3.15.so
cyborgdb_lite.libs/libopenblasp-r0-e3ea6fd1.3.15.so
cyborgdb_lite.libs/libpcre2-8-8701a61e.so.0.7.1
cyborgdb_lite.libs/libpq-4e1bcfab.so.5.13
cyborgdb_lite.libs/libpsl-130094ea.so.5.3.1
cyborgdb_lite.libs/libsasl2-076b3c1f.so.3.0.0
cyborgdb_lite.libs/libsatlas-c63fbc84.so.3.10
cyborgdb_lite.libs/libselinux-5700a1fd.so.1
cyborgdb_lite.libs/libssh-5abd6818.so.4.8.7
cyborgdb_lite.libs/libssl-b6e07dfa.so.1.1.1k
cyborgdb_lite.libs/libsuperlu-30a9c0df.so.5.1
cyborgdb_lite.libs/libunistring-be03fd41.so.2.1.0
cyborgdb_lite-0.12.0.dist-info/METADATA
cyborgdb_lite-0.12.0.dist-info/WHEEL
cyborgdb_lite-0.12.0.dist-info/RECORD
