Metadata-Version: 2.2
Name: cyborgdb-lite
Version: 0.12.0
Summary: Evaluation Version of CyborgDB: The Confidential Vector Database
Author: Cyborg Inc.
License: Proprietary
Classifier: Intended Audience :: Developers
Classifier: Intended Audience :: Information Technology
Classifier: Operating System :: OS Independent
Classifier: Programming Language :: Python :: 3
Classifier: Programming Language :: Python :: 3.9
Classifier: Programming Language :: Python :: 3.10
Classifier: Programming Language :: Python :: 3.11
Classifier: Programming Language :: Python :: 3.12
Classifier: Programming Language :: Python :: 3.13
Classifier: Programming Language :: C++
Classifier: Topic :: Database
Classifier: Topic :: Database :: Database Engines/Servers
Classifier: Topic :: Security :: Cryptography
Classifier: Topic :: Software Development :: Libraries
Project-URL: Homepage, https://www.cyborg.co
Project-URL: Documentation, https://docs.cyborg.co
Requires-Python: >=3.9
Requires-Dist: numpy>=1.24.0
Provides-Extra: langchain
Requires-Dist: langchain-core>=0.1.0; extra == "langchain"
Requires-Dist: sentence-transformers>=2.2.0; extra == "langchain"
Provides-Extra: embeddings
Requires-Dist: sentence-transformers>=2.2.0; extra == "embeddings"
Provides-Extra: all
Requires-Dist: langchain-core>=0.1.0; extra == "all"
Requires-Dist: sentence-transformers>=2.2.0; extra == "all"
